<?xml version="1.0"?><api><query><pages><page pageid="1273280" ns="0" title="W.I.T.C.H."><revisions><rev user="125.60.240.211" anon="" timestamp="2009-08-27T08:43:13Z" size="18772" comment="/* Part VI: Ragorlang */"><tags /></rev><rev user="125.60.240.211" anon="" timestamp="2009-08-27T08:36:20Z" size="18772" comment="/* Part V: The Book of Elements */"><tags /></rev><rev user="125.60.240.211" anon="" timestamp="2009-08-27T08:33:23Z" size="18783" comment="/* Part IV: Trial of The Oracle */"><tags /></rev><rev user="125.60.240.211" anon="" timestamp="2009-08-27T08:30:51Z" size="18784" comment="/* Part II: Nerissa&#039;s Revenge */"><tags /></rev><rev user="125.60.240.211" anon="" timestamp="2009-08-27T08:27:04Z" size="18773" comment="/* Part VI: Ragorlang */"><tags /></rev><rev user="120.28.226.193" anon="" timestamp="2009-08-27T08:24:06Z" size="18778" comment="/* Part IV: Endarno */"><tags /></rev><rev user="120.28.226.193" anon="" timestamp="2009-08-27T08:22:36Z" size="18766" comment="/* Part II: Nerissa */"><tags /></rev><rev user="Irmalover" timestamp="2009-08-24T05:46:27Z" size="18754" comment="part 100 belongs to teach 2b Witch"><tags /></rev><rev user="Irmalover" timestamp="2009-08-24T05:45:42Z" size="18737" comment="part 100 still belongs to teach 2b Witch"><tags /></rev><rev user="78.164.246.233" anon="" timestamp="2009-08-19T19:13:33Z" size="18754" comment="/* External links */"><tags /></rev><rev minor="" user="WikHead" timestamp="2009-08-16T18:44:14Z" size="18705" comment="[[WP:RBK|Reverted]] edits by [[Special:Contributions/88.181.116.231|88.181.116.231]] ([[User talk:88.181.116.231|talk]]) to last version by 124.107.145.116"><tags /></rev><rev user="88.181.116.231" anon="" timestamp="2009-08-16T18:43:50Z" size="18798" comment=""><tags><tag>repeating characters</tag></tags></rev><rev user="124.107.145.116" anon="" timestamp="2009-08-15T15:07:51Z" size="18705" comment="/* Part II: Nerissa */"><tags /></rev><rev user="76.188.160.164" anon="" timestamp="2009-08-14T14:10:50Z" size="18705" comment="/* Part VI: Ragorlang */"><tags /></rev><rev user="84.252.55.84" anon="" timestamp="2009-08-10T21:47:26Z" size="18705" comment="/* Part IX: 100% Witch */"><tags /></rev><rev user="84.252.55.84" anon="" timestamp="2009-08-10T19:11:28Z" size="18792" comment="/* Part IX: 100% Witch */"><tags /></rev><rev user="84.252.55.84" anon="" timestamp="2009-08-10T19:10:15Z" size="18776" comment="/* Part IX: 100% Witch */"><tags /></rev><rev user="Anilro" timestamp="2009-08-10T11:51:57Z" size="18705" comment="/* Issues, Titles and Storylines */"><tags /></rev><rev user="84.252.55.84" anon="" timestamp="2009-08-10T09:07:58Z" size="18707" comment="/* Part IX:100 % W.I.T.C.H */"><tags /></rev><rev user="84.252.55.84" anon="" timestamp="2009-08-10T09:07:20Z" size="18710" comment="/* Part VIII: Teach 2b Witch */"><tags /></rev><rev user="84.252.55.84" anon="" timestamp="2009-08-10T09:05:11Z" size="18638" comment="/* Part VIII: Teach 2b Witch */"><tags /></rev><rev user="ParkingWii" timestamp="2009-08-08T14:13:09Z" size="18701" comment="Minor Change in Tekst"><tags /></rev><rev user="24.170.46.182" anon="" timestamp="2009-08-08T09:13:25Z" size="18686" comment="/* Plot holes */"><tags /></rev><rev user="86.144.205.65" anon="" timestamp="2009-08-06T08:53:46Z" size="18868" comment=""><tags /></rev><rev user="84.252.55.141" anon="" timestamp="2009-08-05T20:16:48Z" size="18868" comment=""><tags /></rev><rev user="173.99.33.221" anon="" timestamp="2009-08-05T19:26:52Z" size="18868" comment="/* Part VIII: Teach 2b Witch */"><tags /></rev><rev user="Irmalover" timestamp="2009-08-05T03:49:32Z" size="18859" comment="The official Italian Witch site tells the the Teach 2&lt;sup&lt;b&lt;/sup&gt; Witch saga continues."><tags /></rev><rev user="Irmalover" timestamp="2009-08-05T03:45:25Z" size="18839" comment="/* Part IX */"><tags /></rev><rev user="80.177.40.59" anon="" timestamp="2009-08-04T11:40:23Z" size="18877" comment="/* Comics */  minor grammar nit"><tags /></rev><rev user="84.252.55.141" anon="" timestamp="2009-08-03T14:06:36Z" size="18873" comment="/* Part VIII: Teach 2b Witch */"><tags /></rev><rev user="84.252.55.141" anon="" timestamp="2009-08-03T14:05:33Z" size="18832" comment="/* Jubilee Issue */"><tags><tag>Section blanking</tag></tags></rev><rev user="84.252.55.141" anon="" timestamp="2009-08-03T14:04:19Z" size="18873" comment="/* Jubilee Issue */"><tags /></rev><rev user="99.141.206.144" anon="" timestamp="2009-07-31T18:19:24Z" size="18835" comment="/* Plot holes */"><tags /></rev><rev user="196.12.236.31" anon="" timestamp="2009-07-30T16:39:30Z" size="18653" comment="/* Notes */"><tags /></rev><rev user="70.122.203.150" anon="" timestamp="2009-07-30T06:58:36Z" size="18648" comment=""><tags /></rev><rev user="76.221.98.94" anon="" timestamp="2009-07-29T00:17:16Z" size="18648" comment="/* Comics */"><tags /></rev><rev user="84.252.54.7" anon="" timestamp="2009-07-26T14:36:44Z" size="18552" comment="/* Part IX: Jubilee Issue */"><tags /></rev><rev user="Anilro" timestamp="2009-07-26T14:12:16Z" size="18560" comment=""><tags /></rev><rev user="68.237.177.80" anon="" timestamp="2009-07-19T01:40:27Z" size="18565" comment="/* Characters */"><tags /></rev><rev user="68.237.177.80" anon="" timestamp="2009-07-19T01:40:15Z" size="18566" comment="/* Characters */"><tags /></rev><rev user="Irmalover" timestamp="2009-07-18T14:01:15Z" size="18556" comment="Witch issue 100 doesn&#039;t have the Teach 2&lt;sup&gt;b&lt;/sup&gt; Witch logo."><tags /></rev><rev user="124.217.31.170" anon="" timestamp="2009-07-15T23:45:11Z" size="18532" comment="/* Part VI: Ragorlang */"><tags /></rev><rev user="Damien lanimue" timestamp="2009-07-14T02:54:55Z" size="18531" comment="/* Characters */"><tags /></rev><rev user="Damien lanimue" timestamp="2009-07-14T02:53:31Z" size="18532" comment="/* Characters */"><tags /></rev><rev user="Irmalover" timestamp="2009-07-12T21:36:24Z" size="18211" comment="/* Part VII: New Power */"><tags /></rev><rev user="Irmalover" timestamp="2009-07-12T21:35:43Z" size="18211" comment="/* Part V: The Book of Elements */"><tags /></rev><rev user="Irmalover" timestamp="2009-07-12T21:35:08Z" size="18211" comment="/* Part IV: Endarno */"><tags /></rev><rev user="Irmalover" timestamp="2009-07-12T21:34:16Z" size="18211" comment="Kandrakar, not Candracar"><tags /></rev><rev user="Irmalover" timestamp="2009-07-12T21:32:58Z" size="18211" comment="It is supposed to be Kandrakar; every other spelling is wrong"><tags /></rev><rev user="84.252.54.164" anon="" timestamp="2009-07-09T20:06:03Z" size="18211" comment="/* Part VIII: Teach 2b Witch */"><tags /></rev><rev user="84.252.54.164" anon="" timestamp="2009-07-09T20:05:15Z" size="18195" comment="/* Part IX */"><tags><tag>Section blanking</tag></tags></rev><rev user="211.30.203.7" anon="" timestamp="2009-07-07T02:17:32Z" size="18230" comment=""><tags /></rev><rev user="211.30.203.7" anon="" timestamp="2009-07-07T02:16:46Z" size="18230" comment=""><tags /></rev><rev user="Tandi94" timestamp="2009-07-07T01:55:57Z" size="18230" comment=""><tags><tag>Section blanking</tag></tags></rev><rev user="ParkingWii" timestamp="2009-07-06T19:40:19Z" size="18447" comment="/* Notes */"><tags /></rev><rev user="ParkingWii" timestamp="2009-07-06T19:35:51Z" size="18452" comment=""><tags /></rev><rev user="ParkingWii" timestamp="2009-07-06T19:31:20Z" size="18446" comment="/* Part IX */"><tags /></rev><rev user="213.46.9.165" anon="" timestamp="2009-07-06T17:53:54Z" size="18434" comment=""><tags /></rev><rev user="TPIRFanSteve" timestamp="2009-07-04T01:14:26Z" size="18216" comment="/* Plot holes */"><tags /></rev><rev user="TPIRFanSteve" timestamp="2009-07-04T01:10:50Z" size="18297" comment="/* Notes */"><tags /></rev><rev user="96.235.246.173" anon="" timestamp="2009-07-03T09:09:20Z" size="18298" comment="/* Part VIII: Teach 2b Witch */"><tags /></rev><rev user="96.235.246.173" anon="" timestamp="2009-07-03T06:31:36Z" size="18275" comment="/* Notes */"><tags /></rev><rev user="76.255.181.131" anon="" timestamp="2009-07-02T17:13:49Z" size="18283" comment="/* Plot holes */"><tags /></rev><rev user="94.158.186.72" anon="" timestamp="2009-07-01T18:22:41Z" size="18271" comment="/* Part VIII: Teach 2b Witch */"><tags /></rev><rev user="96.235.246.173" anon="" timestamp="2009-07-01T09:54:07Z" size="18277" comment="/* Part VIII: Teach 2b Witch */"><tags /></rev><rev user="ParkingWii" timestamp="2009-06-29T22:28:14Z" size="18271" comment=""><tags /></rev><rev user="Mikhailov Kusserow" timestamp="2009-06-29T08:51:33Z" size="18335" comment="[[WP:UNDO|Undid]] revision 299275362 by [[Special:Contributions/ParkingWii|ParkingWii]] ([[User talk:ParkingWii|talk]])"><tags /></rev><rev user="ParkingWii" timestamp="2009-06-29T08:45:36Z" size="18268" comment=""><tags /></rev><rev user="Mikhailov Kusserow" timestamp="2009-06-29T08:18:20Z" size="18335" comment="[[WP:UNDO|Undid]] revision 299272358 by [[Special:Contributions/ParkingWii|ParkingWii]] ([[User talk:ParkingWii|talk]])"><tags /></rev><rev minor="" user="ParkingWii" timestamp="2009-06-29T08:15:32Z" size="18330" comment=""><tags /></rev><rev user="220.101.156.236" anon="" timestamp="2009-06-29T07:39:05Z" size="18335" comment="/* Graphic Novels */"><tags /></rev><rev user="220.101.156.236" anon="" timestamp="2009-06-29T07:34:28Z" size="18319" comment="/* Part VII: New Power */"><tags /></rev><rev user="220.101.156.236" anon="" timestamp="2009-06-29T07:33:39Z" size="18320" comment="/* Part VI: Ragorlang */"><tags /></rev><rev user="220.101.156.236" anon="" timestamp="2009-06-29T07:30:22Z" size="18325" comment="/* Part V: The Book of Elements */"><tags /></rev><rev user="220.101.156.236" anon="" timestamp="2009-06-29T07:26:12Z" size="18318" comment="/* Part II: Nerissa */"><tags /></rev><rev user="220.101.156.236" anon="" timestamp="2009-06-29T07:23:29Z" size="18320" comment="/* Part I: The Twelve Portals */"><tags /></rev><rev user="220.101.156.236" anon="" timestamp="2009-06-29T07:12:19Z" size="18318" comment="/* Part I: The Twelve Portals */"><tags /></rev><rev user="220.101.156.236" anon="" timestamp="2009-06-28T06:02:54Z" size="18316" comment="/* Special Issues */"><tags /></rev><rev user="96.246.249.186" anon="" timestamp="2009-06-27T02:15:30Z" size="18291" comment="/* Plot holes */"><tags /></rev><rev minor="" user="SieBot" timestamp="2009-06-24T01:39:31Z" size="18290" comment="robot Adding: [[tl:W.I.T.C.H.]]"><tags /></rev><rev user="94.158.186.72" anon="" timestamp="2009-06-23T21:28:34Z" size="18272" comment="/* Part VIII: Teach 2b Witch */"><tags /></rev><rev user="71.215.194.229" anon="" timestamp="2009-06-22T19:38:48Z" size="18278" comment="/* Part I: The Twelve Portals */"><tags /></rev><rev user="213.46.9.165" anon="" timestamp="2009-06-21T11:42:35Z" size="18281" comment="/* Plot holes */"><tags /></rev><rev user="86.89.205.33" anon="" timestamp="2009-06-21T11:12:14Z" size="18216" comment="/* Notes */"><tags /></rev><rev user="Irmalover" timestamp="2009-06-18T06:03:42Z" size="17443" comment="/* Part VIII: Teach 2b Witch */"><tags /></rev><rev user="Anilro" timestamp="2009-06-16T14:15:55Z" size="17440" comment="/* Influences */"><tags /></rev><rev user="Anilro" timestamp="2009-06-16T09:49:10Z" size="18354" comment="/* Welcome */"><tags /></rev><rev user="173.98.126.99" anon="" timestamp="2009-06-10T15:12:17Z" size="18354" comment="/* Lene Kaaberbøl */"><tags /></rev><rev user="125.225.41.212" anon="" timestamp="2009-06-09T11:14:16Z" size="18354" comment="/* Part VII: New Power */"><tags /></rev><rev user="125.225.41.212" anon="" timestamp="2009-06-09T11:09:37Z" size="18330" comment="/* Part VIII: Teach 2b Witch */"><tags /></rev><rev user="114.181.177.233" anon="" timestamp="2009-06-08T08:28:28Z" size="18268" comment="/* Welcome */"><tags /></rev><rev user="78.159.152.238" anon="" timestamp="2009-06-04T13:48:40Z" size="18268" comment=""><tags /></rev><rev user="78.159.152.238" anon="" timestamp="2009-06-04T13:47:27Z" size="18268" comment="/* Part VIII: Teach 2b Witch */"><tags /></rev><rev user="96.233.245.68" anon="" timestamp="2009-06-04T06:44:50Z" size="18250" comment="/* Part VIII: Teach 2b Witch */"><tags /></rev><rev user="78.159.152.238" anon="" timestamp="2009-06-03T19:02:38Z" size="18244" comment="/* Part IX: */"><tags /></rev><rev user="78.159.152.238" anon="" timestamp="2009-06-03T19:02:19Z" size="18270" comment="/* Part VIII: Teach 2b Witch */"><tags /></rev><rev user="78.159.152.238" anon="" timestamp="2009-06-03T16:18:25Z" size="18265" comment="/* Part IX: */"><tags /></rev><rev user="78.159.152.238" anon="" timestamp="2009-06-03T16:18:01Z" size="18297" comment="/* Part IX: */"><tags /></rev><rev user="96.247.129.4" anon="" timestamp="2009-06-03T03:05:19Z" size="18265" comment="/* Part IX */"><tags /></rev><rev user="96.247.129.4" anon="" timestamp="2009-06-03T03:04:32Z" size="18264" comment="/* Part IX */"><tags /></rev><rev user="ParkingWii" timestamp="2009-05-30T21:25:09Z" size="18274" comment=""><tags /></rev><rev user="ParkingWii" timestamp="2009-05-30T21:22:01Z" size="18272" comment="[[WP:UNDO|Undid]] revision 293387039 by [[Special:Contributions/ParkingWii|ParkingWii]] ([[User talk:ParkingWii|talk]])"><tags /></rev><rev user="ParkingWii" timestamp="2009-05-30T21:18:02Z" size="18274" comment=""><tags /></rev><rev user="78.159.152.238" anon="" timestamp="2009-05-28T16:42:23Z" size="18272" comment="/* Part IX */"><tags /></rev><rev user="74.72.93.36" anon="" timestamp="2009-05-24T19:56:01Z" size="18273" comment=""><tags /></rev><rev user="74.72.93.36" anon="" timestamp="2009-05-24T19:54:14Z" size="18297" comment=""><tags /></rev><rev user="Headbomb" timestamp="2009-05-23T03:18:29Z" size="18274" comment="WITCH"><tags /></rev><rev user="84.252.18.240" anon="" timestamp="2009-05-20T10:24:26Z" size="18211" comment=""><tags /></rev><rev user="78.159.152.238" anon="" timestamp="2009-05-20T09:08:53Z" size="18211" comment="/* Part VIII: Teach 2b Witch */"><tags /></rev><rev user="71.240.222.70" anon="" timestamp="2009-05-18T22:16:17Z" size="18192" comment="/* Part VIII: Teach 2b Witch */"><tags /></rev><rev user="174.48.175.15" anon="" timestamp="2009-05-18T15:17:45Z" size="18198" comment=""><tags /></rev><rev user="Irmafan001" timestamp="2009-05-18T10:33:43Z" size="18198" comment="/* Welcome */"><tags /></rev><rev user="70.29.124.42" anon="" timestamp="2009-05-17T20:11:39Z" size="18134" comment=""><tags /></rev><rev minor="" user="D6" timestamp="2009-05-08T06:26:37Z" size="18126" comment="fix headline ([[Wikipedia:WikiProject_Check_Wikipedia|WikiProject Check Wikipedia]] check #57"><tags /></rev><rev user="78.159.152.238" anon="" timestamp="2009-05-07T09:00:17Z" size="18125" comment="/* Part IX: Coming soon.... */"><tags /></rev><rev user="202.152.82.169" anon="" timestamp="2009-05-07T08:27:33Z" size="18135" comment="/* Part IX */"><tags /></rev><rev user="Irmalover" timestamp="2009-05-06T20:58:55Z" size="18118" comment=""><tags /></rev><rev user="87.208.244.206" anon="" timestamp="2009-05-06T20:55:40Z" size="18118" comment="/* Part II: Nerissa */"><tags /></rev><rev user="87.208.244.206" anon="" timestamp="2009-05-06T20:54:51Z" size="18118" comment="/* Part II: Nerissa */"><tags /></rev><rev user="87.208.244.206" anon="" timestamp="2009-05-06T20:54:12Z" size="18118" comment="/* Part II: Nerissa */"><tags /></rev><rev user="78.159.152.238" anon="" timestamp="2009-05-06T13:24:06Z" size="18118" comment="/* Part IX */"><tags /></rev><rev user="96.247.132.2" anon="" timestamp="2009-05-04T04:12:24Z" size="18178" comment="/* Part IX */"><tags /></rev><rev user="78.159.152.238" anon="" timestamp="2009-04-27T16:07:18Z" size="18122" comment=""><tags /></rev><rev user="24.21.36.65" anon="" timestamp="2009-04-24T01:28:07Z" size="18122" comment="/* Part VIII: Teach 2b Witch */"><tags /></rev><rev user="65.78.2.191" anon="" timestamp="2009-04-20T13:54:03Z" size="18120" comment=""><tags /></rev><rev minor="" user="ClueBot" timestamp="2009-04-19T11:05:33Z" size="18120" comment="Reverting possible vandalism by [[Special:Contributions/86.139.168.51|86.139.168.51]] to version by 97.118.106.14. False positive? [[User:ClueBot/FalsePositives|Report it]]. Thanks, [[User:ClueBot|ClueBot]]. (674958) (Bot)"><tags /></rev><rev user="86.139.168.51" anon="" timestamp="2009-04-19T11:05:28Z" size="18195" comment=""><tags /></rev><rev user="97.118.106.14" anon="" timestamp="2009-04-12T23:18:27Z" size="18120" comment=""><tags /></rev><rev minor="" user="Download" timestamp="2009-04-12T19:53:53Z" size="18122" comment="cleanup, typos fixed: english → English (2) using [[Project:AutoWikiBrowser|AWB]]"><tags /></rev><rev user="78.159.152.238" anon="" timestamp="2009-04-12T12:14:05Z" size="18122" comment="/* Part VIII: Teach 2b Witch */"><tags /></rev><rev user="78.159.152.238" anon="" timestamp="2009-04-12T12:02:22Z" size="17912" comment="/* Part VIII: Teach 2b Witch */"><tags /></rev><rev minor="" user="TravisAF" timestamp="2009-04-12T11:14:58Z" size="17889" comment="Reverted edits by [[Special:Contributions/82.72.16.143|82.72.16.143]] to last revision by 80.225.78.228 ([[WP:HG|HG]])"><tags /></rev><rev user="82.72.16.143" anon="" timestamp="2009-04-12T11:14:49Z" size="18513" comment="/* Part VI: Ragorlang */"><tags /></rev><rev user="80.225.78.228" anon="" timestamp="2009-04-08T16:42:05Z" size="17889" comment="/* Welcome */"><tags /></rev><rev user="122.3.81.1" anon="" timestamp="2009-04-04T03:36:35Z" size="17889" comment="/* Part VI: Ragorlang */"><tags /></rev><rev minor="" user="TravisAF" timestamp="2009-04-02T12:14:16Z" size="17889" comment="Reverted edits by [[Special:Contributions/89.210.207.137|89.210.207.137]] to last revision by Irmalover ([[WP:HG|HG]])"><tags /></rev><rev user="89.210.207.137" anon="" timestamp="2009-04-02T12:13:50Z" size="17915" comment="/* Part VIII: Teach 2b Witch */"><tags /></rev><rev user="Irmalover" timestamp="2009-03-25T14:30:49Z" size="17889" comment="spoiler alert"><tags /></rev><rev user="Irmalover" timestamp="2009-03-23T12:12:20Z" size="18118" comment="historical addition."><tags /></rev><rev user="78.159.152.238" anon="" timestamp="2009-03-19T16:43:36Z" size="18040" comment="/* Part VIII: Teach 2b Witch */"><tags /></rev><rev user="Luke Warmwater101" timestamp="2009-03-18T02:34:55Z" size="18008" comment="minor word change"><tags /></rev><rev user="Luke Warmwater101" timestamp="2009-03-18T02:33:12Z" size="18006" comment="changed sentence structure"><tags /></rev><rev user="87.222.135.153" anon="" timestamp="2009-03-15T13:51:03Z" size="18021" comment=""><tags /></rev><rev user="58.165.56.175" anon="" timestamp="2009-03-15T09:31:21Z" size="18021" comment=""><tags /></rev><rev user="79.101.68.65" anon="" timestamp="2009-03-04T15:03:42Z" size="17954" comment=""><tags /></rev><rev user="78.159.152.238" anon="" timestamp="2009-03-04T10:51:14Z" size="17954" comment="/* Part VIII: Teach 2b Witch */"><tags /></rev><rev user="Hotcrocodile" timestamp="2009-03-02T07:52:44Z" size="17938" comment="Reverted 1 edit by [[Special:Contributions/202.150.117.223|202.150.117.223]]; Rv junk. ([[WP:TW|TW]])"><tags /></rev><rev user="202.150.117.223" anon="" timestamp="2009-03-02T07:50:24Z" size="17980" comment="/* Graphic Novels */"><tags /></rev><rev user="Anilro" timestamp="2009-02-19T04:00:09Z" size="17938" comment="/* Welcome */"><tags /></rev><rev user="79.72.170.187" anon="" timestamp="2009-02-18T18:27:02Z" size="17938" comment="/* WElcome */"><tags /></rev><rev user="213.84.107.198" anon="" timestamp="2009-02-16T10:29:01Z" size="17938" comment="too premature"><tags /></rev><rev user="85.100.203.95" anon="" timestamp="2009-02-15T15:28:43Z" size="17981" comment="/* Influences */"><tags /></rev><rev user="78.159.152.238" anon="" timestamp="2009-02-15T14:13:57Z" size="17981" comment="/* Comics */"><tags /></rev><rev user="78.159.152.238" anon="" timestamp="2009-02-15T09:59:02Z" size="17981" comment="/* Part IX */"><tags /></rev><rev user="Anilro" timestamp="2009-02-13T15:23:42Z" size="17965" comment=""><tags /></rev><rev user="76.240.222.68" anon="" timestamp="2009-02-12T18:19:35Z" size="17968" comment=""><tags /></rev><rev user="213.46.9.165" anon="" timestamp="2009-02-11T15:28:54Z" size="18323" comment=""><tags /></rev><rev user="213.46.9.165" anon="" timestamp="2009-02-11T15:27:06Z" size="18179" comment=""><tags /></rev><rev user="Anilro" timestamp="2009-02-08T11:21:39Z" size="17966" comment="/* Magical items */"><tags /></rev><rev user="96.233.254.101" anon="" timestamp="2009-02-08T01:06:48Z" size="21255" comment="/* Part IX */"><tags /></rev><rev user="96.233.254.101" anon="" timestamp="2009-02-08T01:06:08Z" size="21243" comment="/* Part VIII: Teach 2b Witch */"><tags /></rev><rev user="24.218.179.78" anon="" timestamp="2009-02-07T22:29:40Z" size="21226" comment="/* External links */"><tags /></rev><rev user="24.218.179.78" anon="" timestamp="2009-02-07T22:12:11Z" size="21259" comment="/* External links */"><tags /></rev><rev user="91.111.191.148" anon="" timestamp="2009-02-06T20:07:00Z" size="21225" comment="/* Influences */"><tags /></rev><rev user="Anilro" timestamp="2009-02-06T11:43:28Z" size="21225" comment=""><tags /></rev><rev minor="" user="SmackBot" timestamp="2009-02-05T02:20:13Z" size="62666" comment="Date maintenance tags and general  fixes"><tags /></rev><rev minor="" user="MelonBot" timestamp="2009-02-04T22:02:09Z" size="62650" comment="Updating {{[[Template:Cite web|cite web]]}} templates: replaced &#039;accessdaymonth/monthday/year&#039; parameters with &#039;accessdate&#039; and &#039;dateformat&#039;"><tags /></rev><rev user="78.159.152.238" anon="" timestamp="2009-02-04T12:39:53Z" size="62650" comment="/* Part VII villains */"><tags /></rev><rev user="78.159.152.238" anon="" timestamp="2009-02-04T12:29:19Z" size="62500" comment="/* Part VII villains */"><tags /></rev><rev user="78.159.152.238" anon="" timestamp="2009-02-04T12:27:19Z" size="62528" comment="/* Part VII villains */"><tags /></rev><rev user="Cailunet" timestamp="2009-02-04T04:33:38Z" size="62500" comment="Restoring tags removed without reasons stated."><tags /></rev><rev user="Cailunet" timestamp="2009-02-04T04:30:51Z" size="62285" comment=""><tags /></rev><rev user="99.144.208.20" anon="" timestamp="2009-02-04T03:10:47Z" size="62269" comment="/* Notes */"><tags /></rev><rev user="85.243.141.26" anon="" timestamp="2009-02-03T23:18:26Z" size="62192" comment="/* Part I villains */"><tags /></rev><rev user="85.243.141.26" anon="" timestamp="2009-02-03T23:14:47Z" size="62182" comment=""><tags /></rev><rev user="78.159.152.238" anon="" timestamp="2009-02-03T10:26:39Z" size="62172" comment="/* Part VIII: Teach 2b Witch */"><tags /></rev><rev user="Lowellian" timestamp="2009-02-02T07:52:23Z" size="62158" comment=""><tags /></rev><rev user="91.110.98.17" anon="" timestamp="2009-02-01T21:22:04Z" size="62148" comment="/* External links */"><tags /></rev><rev user="91.110.98.17" anon="" timestamp="2009-02-01T21:21:04Z" size="62100" comment="/* Notes */"><tags /></rev><rev user="TPIRFanSteve" timestamp="2009-02-01T09:05:16Z" size="62109" comment="/* Notes */"><tags /></rev><rev user="TPIRFanSteve" timestamp="2009-02-01T09:02:50Z" size="62191" comment="/* Notes */ Deleted gibberish."><tags /></rev><rev user="TPIRFanSteve" timestamp="2009-02-01T09:01:02Z" size="62294" comment="/* The Boys */"><tags /></rev><rev user="TPIRFanSteve" timestamp="2009-02-01T08:59:31Z" size="62335" comment="/* Part VII villains */"><tags /></rev><rev user="78.159.152.238" anon="" timestamp="2009-01-31T12:11:11Z" size="62337" comment="/* Part VIII villains */"><tags /></rev><rev user="95.42.171.77" anon="" timestamp="2009-01-30T20:43:06Z" size="62632" comment="/* Part VIII villains */"><tags /></rev><rev user="95.42.171.77" anon="" timestamp="2009-01-30T18:38:07Z" size="62391" comment="/* Part VII villains */"><tags /></rev><rev minor="" user="SmackBot" timestamp="2009-01-29T10:45:49Z" size="62336" comment="Date maintenance tags and general  fixes"><tags /></rev><rev user="Cailunet" timestamp="2009-01-29T02:32:32Z" size="62318" comment="/* Part VII villains */"><tags /></rev><rev user="Piano non troppo" timestamp="2009-01-27T03:57:17Z" size="62361" comment="Reverted edits by [[Special:Contributions/121.208.171.58|121.208.171.58]] ([[User talk:121.208.171.58|talk]]) using [[User:MichaelBillington/MWT|MWT]]"><tags /></rev><rev user="121.208.171.58" anon="" timestamp="2009-01-27T03:56:23Z" size="62456" comment=""><tags /></rev><rev minor="" user="NrDg" timestamp="2009-01-25T02:38:55Z" size="62361" comment="Reverted 1 edit by [[Special:Contributions/Anitrain|Anitrain]]; Spam. ([[WP:TW|TW]])"><tags /></rev><rev user="Anitrain" timestamp="2009-01-25T02:32:17Z" size="62456" comment="/* External links */"><tags /></rev><rev user="193.147.239.254" anon="" timestamp="2009-01-22T13:24:45Z" size="62361" comment="/* Main Characters */"><tags /></rev><rev user="78.159.152.238" anon="" timestamp="2009-01-19T12:53:51Z" size="62360" comment="/* Part VII villains */"><tags /></rev><rev user="Irmalover" timestamp="2009-01-19T09:02:48Z" size="62361" comment="irrelevant information"><tags /></rev><rev user="Irmalover" timestamp="2009-01-19T08:56:18Z" size="62400" comment="too early. this is a spoiler."><tags /></rev><rev user="Irmalover" timestamp="2009-01-19T08:55:15Z" size="62728" comment="when she&#039;s angry, Irma is cursing or calling names."><tags /></rev><rev user="99.144.208.20" anon="" timestamp="2009-01-19T00:25:09Z" size="62628" comment="/* Main Characters */"><tags /></rev><rev user="99.144.208.20" anon="" timestamp="2009-01-18T18:16:41Z" size="62625" comment="/* Notes */"><tags /></rev><rev user="99.144.208.20" anon="" timestamp="2009-01-18T18:05:46Z" size="62522" comment="/* Main Characters */"><tags /></rev><rev user="99.144.208.20" anon="" timestamp="2009-01-18T18:01:49Z" size="62520" comment="/* Main Characters */"><tags /></rev><rev user="89.31.118.254" anon="" timestamp="2009-01-18T09:06:19Z" size="62519" comment="You cut out too much info"><tags /></rev><rev user="70.58.218.98" anon="" timestamp="2009-01-18T07:00:49Z" size="58412" comment=""><tags /></rev><rev user="Melina Lopez" timestamp="2009-01-17T22:27:55Z" size="62519" comment="/* Main Characters */"><tags /></rev><rev user="98.122.124.155" anon="" timestamp="2009-01-17T18:28:42Z" size="62532" comment="/* Main Characters */"><tags /></rev><rev user="24.185.70.26" anon="" timestamp="2009-01-17T17:04:01Z" size="62532" comment="/* Main Characters */"><tags /></rev><rev user="89.31.118.254" anon="" timestamp="2009-01-17T08:44:04Z" size="62171" comment="/* Main Characters */"><tags /></rev><rev user="Irmalover" timestamp="2009-01-15T10:38:11Z" size="62011" comment="All of the girls have used their powers for personal gain."><tags /></rev><rev user="Irmalover" timestamp="2009-01-15T10:31:58Z" size="62096" comment="Orube is not a main character."><tags /></rev><rev user="213.84.107.198" anon="" timestamp="2009-01-15T10:24:56Z" size="62105" comment="better translation"><tags /></rev><rev user="Sweet Autumn Misery" timestamp="2009-01-15T07:08:48Z" size="62116" comment=""><tags /></rev><rev user="Sweet Autumn Misery" timestamp="2009-01-15T07:04:57Z" size="62123" comment=""><tags /></rev><rev user="Sweet Autumn Misery" timestamp="2009-01-15T07:00:12Z" size="62068" comment=""><tags /></rev><rev user="Sweet Autumn Misery" timestamp="2009-01-15T06:59:31Z" size="62083" comment=""><tags /></rev><rev user="Sweet Autumn Misery" timestamp="2009-01-15T06:50:04Z" size="62078" comment=""><tags /></rev><rev user="78.159.152.238" anon="" timestamp="2009-01-14T14:02:07Z" size="62293" comment="/* Part VIII: Teach 2b Witch */"><tags /></rev><rev minor="" user="SmackBot" timestamp="2009-01-09T04:14:44Z" size="62267" comment="Date maintenance tags and general  fixes"><tags /></rev><rev user="Cailunet" timestamp="2009-01-09T01:44:50Z" size="62249" comment=""><tags /></rev><rev minor="" user="SmackBot" timestamp="2009-01-06T01:50:15Z" size="62208" comment="Date maintenance tags and general  fixes"><tags /></rev><rev user="96.247.129.161" anon="" timestamp="2009-01-04T21:12:33Z" size="62220" comment="/* Part VIII: Teach 2b Witch */"><tags /></rev><rev user="72.53.66.68" anon="" timestamp="2009-01-02T23:43:50Z" size="62200" comment="/* Main Characters */"><tags /></rev><rev user="TPIRFanSteve" timestamp="2009-01-01T06:25:05Z" size="62200" comment="/* Notes */"><tags /></rev><rev user="TPIRFanSteve" timestamp="2009-01-01T06:24:15Z" size="62199" comment="/* Magical items */"><tags /></rev><rev user="TPIRFanSteve" timestamp="2009-01-01T06:21:47Z" size="62203" comment="/* The Boys */"><tags /></rev><rev user="TPIRFanSteve" timestamp="2009-01-01T06:19:48Z" size="62214" comment="/* Main Characters */"><tags /></rev><rev user="96.242.254.194" anon="" timestamp="2008-12-30T18:10:51Z" size="62210" comment="/* Main Characters */"><tags /></rev><rev user="96.235.242.134" anon="" timestamp="2008-12-28T07:54:48Z" size="62130" comment="/* Notes */"><tags /></rev><rev user="Anilro" timestamp="2008-12-27T03:23:12Z" size="62069" comment="/* Video Game */"><tags /></rev><rev user="68.106.216.86" anon="" timestamp="2008-12-23T01:21:11Z" size="62036" comment="/* Main Characters */"><tags /></rev><rev user="86.142.245.22" anon="" timestamp="2008-12-21T06:08:37Z" size="62109" comment="/* Main Characters */ grammar"><tags /></rev><rev user="119.93.175.200" anon="" timestamp="2008-12-16T06:12:36Z" size="62106" comment=""><tags /></rev><rev user="148.83.132.170" anon="" timestamp="2008-12-14T14:43:49Z" size="62106" comment="/* Part I villains */"><tags /></rev><rev user="96.235.245.232" anon="" timestamp="2008-12-10T03:11:03Z" size="62098" comment="/* Part VIII: Teach 2b Witch */"><tags /></rev><rev user="Yriafy" timestamp="2008-12-08T01:40:49Z" size="62093" comment="/* Council/Congregation of Kandrakar */"><tags /></rev><rev user="Yriafy" timestamp="2008-12-08T01:34:52Z" size="62033" comment="/* Magical items */"><tags /></rev><rev user="Yriafy" timestamp="2008-12-08T01:29:36Z" size="61589" comment="/* Part VIII: Teach 2b Witch */"><tags /></rev><rev user="Yriafy" timestamp="2008-12-08T01:25:44Z" size="61376" comment="/* Part VII: New Power */"><tags /></rev><rev user="Yriafy" timestamp="2008-12-08T01:24:17Z" size="61252" comment="/* Part VII villains */"><tags /></rev><rev user="Yriafy" timestamp="2008-12-08T01:22:37Z" size="61248" comment=""><tags /></rev><rev user="78.159.152.238" anon="" timestamp="2008-12-05T10:38:14Z" size="61209" comment="/* Part VII villains */"><tags /></rev><rev user="78.159.152.238" anon="" timestamp="2008-12-05T09:00:39Z" size="61214" comment="/* Part VIII: Teach 2b Witch */"><tags /></rev><rev user="78.159.152.238" anon="" timestamp="2008-12-04T10:47:47Z" size="61191" comment="/* Part VІІІ villains */"><tags /></rev><rev user="114.108.255.49" anon="" timestamp="2008-12-04T01:22:37Z" size="61192" comment="/* Part VІІІ villains */"><tags /></rev><rev user="78.159.152.238" anon="" timestamp="2008-12-03T15:29:13Z" size="61193" comment="/* Part VII villains */"><tags /></rev><rev user="78.159.152.238" anon="" timestamp="2008-12-03T12:37:36Z" size="61193" comment="/* Part VII villains */"><tags /></rev><rev user="78.159.152.238" anon="" timestamp="2008-12-03T12:37:15Z" size="60905" comment="/* Part VІІІ villains */"><tags /></rev><rev user="78.159.152.238" anon="" timestamp="2008-12-03T12:36:10Z" size="61195" comment="/* Part VII villains */"><tags /></rev><rev user="78.159.152.238" anon="" timestamp="2008-12-03T12:28:44Z" size="60900" comment="/* Part VII villains */"><tags /></rev><rev user="78.159.152.238" anon="" timestamp="2008-12-02T11:37:04Z" size="60725" comment="/* Part VII villains */"><tags /></rev><rev user="TPIRFanSteve" timestamp="2008-12-01T23:25:13Z" size="61035" comment="/* Notes */"><tags /></rev><rev user="TPIRFanSteve" timestamp="2008-12-01T23:23:02Z" size="61009" comment="/* Part V: The Book of Elements */"><tags /></rev><rev user="TPIRFanSteve" timestamp="2008-12-01T23:21:48Z" size="60998" comment="/* Part VII villains */"><tags /></rev><rev user="84.13.124.15" anon="" timestamp="2008-11-30T20:28:45Z" size="61045" comment="/* Video Game */"><tags /></rev><rev user="76.78.59.231" anon="" timestamp="2008-11-26T05:06:15Z" size="60993" comment="/* Main Characters */"><tags /></rev><rev minor="" user="Evilandi" timestamp="2008-11-25T16:55:25Z" size="60990" comment="dab WITCH (Computer)"><tags /></rev><rev user="Mufka" timestamp="2008-11-24T23:49:23Z" size="60928" comment="refs"><tags /></rev><rev user="78.159.152.238" anon="" timestamp="2008-11-24T15:46:28Z" size="60903" comment="/* Part VI villains */"><tags /></rev><rev user="78.159.152.238" anon="" timestamp="2008-11-24T15:45:13Z" size="60908" comment="/* Part VI villains */"><tags /></rev><rev user="78.159.152.238" anon="" timestamp="2008-11-24T15:44:31Z" size="60908" comment="/* Part VI villains */"><tags /></rev><rev user="78.159.152.238" anon="" timestamp="2008-11-24T15:42:18Z" size="60909" comment="/* Part VI villains */"><tags /></rev><rev user="69.179.57.30" anon="" timestamp="2008-11-22T03:05:29Z" size="60560" comment="/* Main Characters */"><tags /></rev><rev user="Webwarlock" timestamp="2008-11-18T22:39:00Z" size="60563" comment="Revert to revision 252220589 dated 2008-11-16 20:53:19 by 92.0.109.241 using [[:en:Wikipedia:Tools/Navigation_popups|popups]]"><tags /></rev><rev user="65.34.28.130" anon="" timestamp="2008-11-18T22:36:31Z" size="60571" comment="name"><tags /></rev><rev user="92.0.109.241" anon="" timestamp="2008-11-16T20:53:19Z" size="60563" comment=""><tags /></rev><rev user="72.248.5.117" anon="" timestamp="2008-11-16T20:04:51Z" size="60596" comment="/* Former Guardians */"><tags /></rev><rev user="72.248.5.117" anon="" timestamp="2008-11-16T20:04:32Z" size="60592" comment="/* Former Guardians */"><tags /></rev><rev user="92.0.109.241" anon="" timestamp="2008-11-15T21:58:36Z" size="60588" comment=""><tags /></rev><rev user="96.235.241.88" anon="" timestamp="2008-11-13T05:36:18Z" size="60795" comment="/* Part VIII: Teach 2b Witch */"><tags /></rev><rev user="FairuseBot" timestamp="2008-11-11T06:06:34Z" size="60790" comment="Removing [[:Image:Welcome11.jpg|image]] with inadequate [[WP:NFCC|rationale]]"><tags /></rev><rev user="Irmalover" timestamp="2008-11-10T21:36:38Z" size="60740" comment="correction towards the storyline"><tags /></rev><rev user="Irmalover" timestamp="2008-11-10T20:58:58Z" size="60733" comment="/* Notes */"><tags /></rev><rev user="125.60.243.89" anon="" timestamp="2008-11-09T14:11:15Z" size="60636" comment="/* Part VII villains */"><tags /></rev><rev user="89.31.118.254" anon="" timestamp="2008-11-09T09:00:21Z" size="60638" comment="/* Main Characters */"><tags /></rev><rev user="TPIRFanSteve" timestamp="2008-11-09T05:00:09Z" size="60585" comment="/* Part VIII: Teach 2b Witch */"><tags /></rev><rev user="78.159.152.238" anon="" timestamp="2008-11-06T19:44:30Z" size="60585" comment="/* Part VIII: Teach 2b Witch */"><tags /></rev><rev user="Irmalover" timestamp="2008-11-06T09:20:52Z" size="60574" comment="Part VIII readded"><tags /></rev><rev user="Irmalover" timestamp="2008-11-05T23:07:50Z" size="60187" comment="the correct spelling is Kandrakar."><tags /></rev><rev user="87.208.244.206" anon="" timestamp="2008-11-05T23:04:41Z" size="60187" comment="reclassified into comics, graphic novels, special issues and books"><tags /></rev><rev user="213.84.107.198" anon="" timestamp="2008-11-05T13:54:57Z" size="60160" comment="[[WP:UNDO|Undid]] revision 249839137 by [[Special:Contributions/213.84.107.198|213.84.107.198]] ([[User talk:213.84.107.198|talk]])"><tags /></rev><rev user="213.84.107.198" anon="" timestamp="2008-11-05T13:51:26Z" size="60162" comment="reclassification of the comics and chapter books"><tags /></rev><rev user="92.82.187.199" anon="" timestamp="2008-11-03T09:03:11Z" size="60160" comment=""><tags /></rev><rev user="92.82.187.199" anon="" timestamp="2008-11-03T09:00:19Z" size="60265" comment=""><tags /></rev><rev user="76.214.199.2" anon="" timestamp="2008-11-02T15:44:01Z" size="60628" comment="/* Part II villains */"><tags /></rev><rev user="76.214.199.2" anon="" timestamp="2008-11-02T15:39:45Z" size="60628" comment="/* Part I villains */"><tags /></rev><rev user="76.214.199.2" anon="" timestamp="2008-11-02T15:37:19Z" size="60628" comment="/* Former Guardians */"><tags /></rev><rev user="76.214.199.2" anon="" timestamp="2008-11-02T15:35:38Z" size="60628" comment="/* Council/Congregation of Kandrakar */"><tags /></rev><rev user="76.214.199.2" anon="" timestamp="2008-11-02T15:27:36Z" size="60628" comment="/* Main Characters */"><tags /></rev><rev user="TPIRFanSteve" timestamp="2008-11-02T07:44:10Z" size="60628" comment="/* Notes */ Having both bullets and carats is silly."><tags /></rev><rev user="TPIRFanSteve" timestamp="2008-11-02T07:42:56Z" size="60718" comment="/* Lene Kaaberbøl */"><tags /></rev><rev user="TPIRFanSteve" timestamp="2008-11-02T07:41:58Z" size="60719" comment="/* New Power */ This section is completely worthless the way it&#039;s currently written."><tags /></rev><rev user="TPIRFanSteve" timestamp="2008-11-02T07:40:39Z" size="61064" comment="/* Issues, Titles and Storylines */"><tags /></rev><rev user="TPIRFanSteve" timestamp="2008-11-02T07:38:53Z" size="61106" comment="/* The Boys */"><tags /></rev><rev user="78.159.152.238" anon="" timestamp="2008-10-29T15:13:10Z" size="61179" comment="/* Part VIII villains */"><tags /></rev><rev user="78.159.152.238" anon="" timestamp="2008-10-29T15:12:29Z" size="61315" comment="/* Part VIII villains */"><tags /></rev><rev user="78.159.152.238" anon="" timestamp="2008-10-29T15:11:49Z" size="61310" comment="/* Part VIII villains */"><tags /></rev><rev user="78.159.152.238" anon="" timestamp="2008-10-29T15:11:20Z" size="61309" comment="/* Part VIII villains */"><tags /></rev><rev minor="" user="J.delanoy" timestamp="2008-10-29T14:41:26Z" size="61179" comment="Reverted edits by [[Special:Contributions/216.119.5.2|216.119.5.2]] ([[WP:HG|HG]])"><tags /></rev><rev user="216.119.5.2" anon="" timestamp="2008-10-29T14:37:43Z" size="61500" comment="/* References */"><tags /></rev><rev user="216.119.5.2" anon="" timestamp="2008-10-29T14:36:28Z" size="61469" comment=""><tags /></rev><rev user="216.119.5.2" anon="" timestamp="2008-10-29T14:34:19Z" size="61199" comment=""><tags /></rev><rev user="125.60.243.89" anon="" timestamp="2008-10-28T05:05:57Z" size="61179" comment="/* Part VIII: Teach 2b Witch */"><tags /></rev><rev user="78.159.152.238" anon="" timestamp="2008-10-27T11:49:26Z" size="61184" comment="/* Part VIII: Teach 2b Witch */"><tags /></rev><rev user="78.159.152.238" anon="" timestamp="2008-10-27T11:47:26Z" size="61183" comment="/* Part VIII: Teach 2b Witch */"><tags /></rev><rev user="78.159.152.238" anon="" timestamp="2008-10-27T11:44:41Z" size="61176" comment="/* Part VIII: Teach 2b Witch */"><tags /></rev><rev user="78.159.152.238" anon="" timestamp="2008-10-27T11:44:07Z" size="61187" comment="/* Part VIII: Teach 2b Witch */"><tags /></rev><rev user="78.159.152.238" anon="" timestamp="2008-10-27T08:31:56Z" size="61151" comment="/* Part VIII villains */"><tags /></rev><rev user="78.159.152.238" anon="" timestamp="2008-10-25T11:59:43Z" size="61143" comment="/* Part VIII villains */"><tags /></rev><rev user="78.159.152.238" anon="" timestamp="2008-10-25T11:57:44Z" size="61213" comment="/* Part VIII villains */"><tags /></rev><rev user="78.159.152.238" anon="" timestamp="2008-10-25T11:56:02Z" size="61180" comment="/* Part VIII villains */"><tags /></rev><rev user="125.60.243.89" anon="" timestamp="2008-10-24T16:25:58Z" size="61143" comment="/* Part VIII villains */"><tags /></rev><rev user="92.0.109.241" anon="" timestamp="2008-10-22T20:51:29Z" size="61141" comment=""><tags /></rev><rev user="Tony1" timestamp="2008-10-22T12:59:38Z" size="61365" comment="[[User:Lightmouse/monobook.js/script.js|script]]-assisted date/terms audit; see [[Wikipedia:MOSNUM#Date_autoformatting|mosnum]], [[wp:overlink]]"><tags /></rev><rev user="78.159.152.238" anon="" timestamp="2008-10-22T12:59:24Z" size="61405" comment="/* Part VIII villains */"><tags /></rev><rev user="78.159.152.238" anon="" timestamp="2008-10-22T12:56:01Z" size="61362" comment="/* Part VIII villains */"><tags /></rev><rev user="Irmalover" timestamp="2008-10-22T09:23:32Z" size="61334" comment="corresponding to the original title script"><tags /></rev><rev user="Irmalover" timestamp="2008-10-22T09:19:51Z" size="61326" comment="correction of translation"><tags /></rev><rev user="78.159.152.238" anon="" timestamp="2008-10-21T11:39:57Z" size="61333" comment="/* Part VIII: Teach To be Witch */"><tags /></rev><rev user="203.193.207.183" anon="" timestamp="2008-10-20T06:52:38Z" size="61328" comment="/* Other characters */"><tags /></rev><rev user="203.193.207.183" anon="" timestamp="2008-10-20T06:39:15Z" size="61104" comment="/* Part IV villains */"><tags /></rev><rev user="203.193.207.183" anon="" timestamp="2008-10-20T06:38:06Z" size="61165" comment="/* Part IV villains */"><tags /></rev><rev user="86.156.19.254" anon="" timestamp="2008-10-19T14:17:48Z" size="61104" comment="/* Part II: Nerissa */"><tags /></rev><rev user="125.60.243.89" anon="" timestamp="2008-10-15T04:32:21Z" size="61142" comment=""><tags /></rev><rev user="125.60.243.89" anon="" timestamp="2008-10-15T04:14:41Z" size="61146" comment=""><tags /></rev><rev user="125.60.243.89" anon="" timestamp="2008-10-14T13:20:57Z" size="61146" comment="/* Part VII villains */"><tags /></rev><rev user="119.95.54.159" anon="" timestamp="2008-10-14T08:00:39Z" size="61127" comment="/* The Boys */"><tags /></rev><rev user="Piano non troppo" timestamp="2008-10-13T09:17:19Z" size="61282" comment="Removes External links to forum [[WP:LINKSTOAVOID]] and commercial site [[WP:SPAM]]"><tags /></rev><rev user="78.159.152.238" anon="" timestamp="2008-10-13T09:15:54Z" size="61396" comment="/* Part VIII: Teach To be Witch */"><tags /></rev><rev user="78.159.152.238" anon="" timestamp="2008-10-13T09:15:17Z" size="61401" comment="/* Part VIII: Teach To be Witch */"><tags /></rev><rev user="96.233.251.195" anon="" timestamp="2008-10-12T21:47:50Z" size="61396" comment="/* Special Issues */"><tags /></rev><rev user="96.233.251.195" anon="" timestamp="2008-10-12T21:46:44Z" size="61360" comment="/* Special Issues */"><tags /></rev><rev user="96.233.251.195" anon="" timestamp="2008-10-12T21:43:33Z" size="61308" comment="/* =Part VIII villains */"><tags /></rev><rev user="96.233.251.195" anon="" timestamp="2008-10-12T21:43:04Z" size="61309" comment="/* Part VII villains */"><tags /></rev><rev user="78.159.152.238" anon="" timestamp="2008-10-12T16:05:17Z" size="61282" comment="/* Part VIII: Teach To be Witch */"><tags /></rev><rev user="78.159.152.238" anon="" timestamp="2008-10-12T16:04:46Z" size="61282" comment="/* Part VIII: Teach To be Witch */"><tags /></rev><rev minor="" user="Ttony21" timestamp="2008-10-11T15:45:43Z" size="61271" comment="Reverted 1 edit by [[Special:Contributions/86.149.16.211|86.149.16.211]] identified as [[WP:VAND|vandalism]] to last revision by [[User:78.159.152.238|78.159.152.238]]. ([[WP:TW|TW]])"><tags /></rev><rev user="86.149.16.211" anon="" timestamp="2008-10-11T15:45:28Z" size="3530" comment=""><tags /></rev><rev user="78.159.152.238" anon="" timestamp="2008-10-11T15:28:00Z" size="61271" comment="/* Part VII villains */"><tags /></rev><rev user="89.251.107.6" anon="" timestamp="2008-10-11T12:16:11Z" size="61265" comment="/* Video Game */"><tags /></rev><rev user="78.159.152.238" anon="" timestamp="2008-10-10T17:28:28Z" size="61167" comment="/* Part VII villains */"><tags /></rev><rev user="78.159.152.238" anon="" timestamp="2008-10-10T16:49:38Z" size="61109" comment="/* Part VII villains */"><tags /></rev><rev user="131.91.228.43" anon="" timestamp="2008-10-06T17:14:05Z" size="60779" comment="/* Main Characters */"><tags /></rev><rev user="131.91.228.43" anon="" timestamp="2008-10-06T17:13:25Z" size="60775" comment="/* Main Characters */"><tags /></rev><rev user="87.6.233.56" anon="" timestamp="2008-10-05T19:47:27Z" size="60770" comment=""><tags /></rev><rev user="68.209.106.107" anon="" timestamp="2008-10-05T06:59:27Z" size="60888" comment="/* Main Characters */"><tags /></rev><rev user="68.209.106.107" anon="" timestamp="2008-10-05T04:20:44Z" size="60881" comment="/* Video Game */"><tags /></rev><rev minor="" user="Flewis" timestamp="2008-10-04T07:38:23Z" size="60878" comment="Reverted edits by [[Special:Contributions/124.104.97.34|124.104.97.34]] to last version by 86.155.240.69 ([[WP:HG|HG]])"><tags /></rev><rev user="124.104.97.34" anon="" timestamp="2008-10-04T07:37:19Z" size="60896" comment="/* Other characters */"><tags /></rev><rev user="86.155.240.69" anon="" timestamp="2008-10-02T19:43:06Z" size="60878" comment=""><tags /></rev><rev user="86.155.240.69" anon="" timestamp="2008-10-02T19:00:15Z" size="61170" comment="/* Magical items */"><tags /></rev><rev user="86.155.240.69" anon="" timestamp="2008-10-02T19:00:00Z" size="61169" comment="/* Magical items */"><tags /></rev><rev user="86.155.240.69" anon="" timestamp="2008-10-02T18:59:09Z" size="61266" comment="/* Magical items */"><tags /></rev><rev user="96.235.244.163" anon="" timestamp="2008-10-01T04:59:47Z" size="61260" comment="/* Part VIII: Teach To be Witch */"><tags /></rev><rev user="86.128.22.111" anon="" timestamp="2008-09-27T17:13:56Z" size="61255" comment="/* Part VI villains */"><tags /></rev><rev user="68.209.106.107" anon="" timestamp="2008-09-27T15:37:29Z" size="61112" comment="/* The Boys */"><tags /></rev><rev user="68.209.106.107" anon="" timestamp="2008-09-27T15:35:55Z" size="61038" comment="/* Main Characters */"><tags /></rev><rev user="68.209.106.107" anon="" timestamp="2008-09-27T15:34:54Z" size="61042" comment="/* Main Characters */"><tags /></rev><rev user="86.156.9.66" anon="" timestamp="2008-09-25T02:11:57Z" size="61042" comment=""><tags /></rev><rev user="86.156.9.66" anon="" timestamp="2008-09-25T01:27:56Z" size="60997" comment=""><tags /></rev><rev user="202.86.204.114" anon="" timestamp="2008-09-23T01:02:58Z" size="61905" comment="/* Part VII villains */"><tags /></rev><rev user="122.52.18.27" anon="" timestamp="2008-09-22T12:58:39Z" size="61903" comment="/* Special Issues */"><tags /></rev><rev user="125.60.243.89" anon="" timestamp="2008-09-22T12:02:17Z" size="61908" comment="/* Part II: Nerissa */"><tags /></rev><rev user="Irmalover" timestamp="2008-09-22T04:27:38Z" size="61907" comment="additional info"><tags /></rev><rev user="Irmalover" timestamp="2008-09-22T04:17:07Z" size="61817" comment="/* Part VIII: Teach To be Witch */"><tags /></rev><rev user="68.209.106.107" anon="" timestamp="2008-09-21T20:20:28Z" size="61809" comment="/* Main Characters */"><tags /></rev><rev user="24.132.166.101" anon="" timestamp="2008-09-20T16:07:50Z" size="61799" comment=""><tags /></rev><rev user="86.155.34.110" anon="" timestamp="2008-09-20T08:58:04Z" size="61765" comment="/* Main Characters */"><tags /></rev><rev user="83.108.159.34" anon="" timestamp="2008-09-17T19:57:07Z" size="61774" comment="/* Part VII villains */"><tags /></rev><rev user="TPIRFanSteve" timestamp="2008-09-13T16:47:59Z" size="61581" comment="/* Part VII: New Power */"><tags /></rev><rev user="68.209.106.107" anon="" timestamp="2008-09-13T05:53:23Z" size="61580" comment="/* The Boys */"><tags /></rev><rev user="68.209.106.107" anon="" timestamp="2008-09-13T05:52:38Z" size="61596" comment="/* Former Guardians */"><tags /></rev><rev user="125.60.243.89" anon="" timestamp="2008-09-12T12:20:37Z" size="61616" comment="/* Part VIII: Teach To be Witch */"><tags /></rev><rev user="125.60.243.89" anon="" timestamp="2008-09-12T12:14:29Z" size="61620" comment="/* External links */"><tags /></rev><rev user="125.60.243.89" anon="" timestamp="2008-09-12T12:12:34Z" size="61714" comment=""><tags /></rev><rev user="125.60.243.89" anon="" timestamp="2008-09-12T12:11:22Z" size="61714" comment="/* Part VIII: Teach To be Witch */"><tags /></rev><rev user="203.84.180.62" anon="" timestamp="2008-09-05T12:09:25Z" size="61696" comment="/* Part VII: New Power */"><tags /></rev><rev user="202.86.204.114" anon="" timestamp="2008-09-04T01:04:59Z" size="61699" comment="/* Other characters */"><tags /></rev><rev minor="" user="Cydebot" timestamp="2008-09-03T03:26:56Z" size="62205" comment="Robot - Moving category Italian comic book titles to Italian comics titles per [[WP:CFD|CFD]] at [[Wikipedia:Categories for discussion/Log/2008 August 28]]."><tags /></rev><rev user="Irmalover" timestamp="2008-09-02T19:43:03Z" size="62209" comment="Proper translation of the title from Italian to English"><tags /></rev><rev user="76.188.166.192" anon="" timestamp="2008-09-02T19:09:29Z" size="62212" comment="/* Notes */"><tags /></rev><rev user="206.53.144.74" anon="" timestamp="2008-08-31T04:01:50Z" size="62212" comment="/* Part VII: New Power */"><tags /></rev><rev user="87.208.244.206" anon="" timestamp="2008-08-31T02:53:07Z" size="62147" comment="turning the text to bold"><tags /></rev><rev user="202.86.204.114" anon="" timestamp="2008-08-29T02:05:56Z" size="62137" comment="/* Characters */"><tags /></rev><rev user="99.227.33.192" anon="" timestamp="2008-08-28T13:59:04Z" size="62232" comment=""><tags /></rev><rev user="58.111.72.118" anon="" timestamp="2008-08-22T05:36:05Z" size="62138" comment="/* Influences */"><tags /></rev><rev user="69.142.226.95" anon="" timestamp="2008-08-20T03:16:28Z" size="62138" comment="/* Special Issues */"><tags /></rev><rev user="Irmalover" timestamp="2008-08-19T05:18:18Z" size="62162" comment="/* Main Characters */"><tags /></rev><rev user="96.235.240.119" anon="" timestamp="2008-08-18T19:52:49Z" size="62452" comment="/* Part VIII: Teach To be Witch */"><tags /></rev><rev user="167.197.117.122" anon="" timestamp="2008-08-18T19:51:40Z" size="62447" comment="Spelling"><tags /></rev><rev user="TPIRFanSteve" timestamp="2008-08-18T05:54:51Z" size="62445" comment="/* Former Guardians */"><tags /></rev><rev user="Irmalover" timestamp="2008-08-16T08:35:59Z" size="62523" comment="the Olympic Games special is released since 7-24-2008"><tags /></rev><rev user="Irmalover" timestamp="2008-08-16T08:30:21Z" size="62499" comment="/* Part VIII: Teach To be Witch */ newest issue title is added"><tags /></rev><rev minor="" user="ToxicAllure" timestamp="2008-08-16T06:54:59Z" size="62474" comment="/* The Boys */  spelling error fixed"><tags /></rev><rev user="12.216.169.247" anon="" timestamp="2008-08-16T00:59:23Z" size="62473" comment="/* The Boys */"><tags /></rev><rev minor="" user="Kipoc" timestamp="2008-08-15T07:02:46Z" size="62575" comment="Typo correction. [[Wikipedia:Typo|You can help!]]"><tags /></rev><rev minor="" user="Cp111" timestamp="2008-08-14T20:06:06Z" size="62574" comment="/* Characters */"><tags /></rev><rev user="119.11.49.67" anon="" timestamp="2008-08-14T05:43:54Z" size="62578" comment="/* Part II villains */"><tags /></rev><rev user="83.255.17.203" anon="" timestamp="2008-08-13T13:40:24Z" size="62574" comment="/* The Boys */"><tags /></rev><rev user="83.255.17.203" anon="" timestamp="2008-08-13T13:33:33Z" size="62314" comment="/* Guardians */"><tags /></rev><rev minor="" user="About123" timestamp="2008-08-12T19:56:36Z" size="62193" comment=""><tags /></rev><rev user="201.51.212.231" anon="" timestamp="2008-08-11T04:19:57Z" size="62169" comment=""><tags /></rev><rev user="201.51.212.231" anon="" timestamp="2008-08-11T04:19:28Z" size="62170" comment="/* Part IV villains */"><tags /></rev><rev user="203.84.180.62" anon="" timestamp="2008-08-08T12:42:41Z" size="62167" comment=""><tags /></rev><rev user="122.52.147.25" anon="" timestamp="2008-08-08T04:26:50Z" size="62167" comment="/* Part VII: New Power */"><tags /></rev><rev user="122.52.147.25" anon="" timestamp="2008-08-08T04:26:35Z" size="62167" comment="/* Part VII: New Power */"><tags /></rev><rev user="122.52.147.25" anon="" timestamp="2008-08-08T04:25:52Z" size="62166" comment="/* Part VIII: Teach 2b Witch */"><tags /></rev><rev user="86.151.91.91" anon="" timestamp="2008-08-03T16:09:15Z" size="62163" comment="/* Villains */"><tags /></rev><rev user="86.151.91.91" anon="" timestamp="2008-08-03T16:06:38Z" size="62087" comment="/* Characters */"><tags /></rev><rev user="Kandrakar" timestamp="2008-08-03T09:41:35Z" size="61992" comment="/* Part V: The Book of Elements */"><tags /></rev><rev user="Kandrakar" timestamp="2008-08-03T09:41:02Z" size="61990" comment="/* Part VI: Ragorlang */"><tags /></rev><rev user="81.158.201.247" anon="" timestamp="2008-08-02T13:12:45Z" size="61989" comment="/* Books */"><tags /></rev><rev user="81.158.201.247" anon="" timestamp="2008-08-02T13:11:51Z" size="61988" comment="/* Books */"><tags /></rev><rev user="96.235.230.33" anon="" timestamp="2008-08-01T06:31:11Z" size="61960" comment="/* Part VIII: Teach 2b Witch */"><tags /></rev><rev user="Blunk" timestamp="2008-07-31T20:20:40Z" size="61955" comment="[[WP:UNDO|Undid]] revision 228825686 by [[Special:Contributions/88.106.116.248|88.106.116.248]] ([[User talk:88.106.116.248|talk]])"><tags /></rev><rev minor="" user="Irmalover" timestamp="2008-07-31T17:28:32Z" size="62053" comment="/* Notes */"><tags /></rev><rev user="Irmalover" timestamp="2008-07-31T16:51:54Z" size="62054" comment="The girl is not named Laura but Lora. This can be found in Witch issue 79."><tags /></rev><rev user="88.106.116.248" anon="" timestamp="2008-07-30T15:31:24Z" size="62055" comment="/* External links */"><tags /></rev><rev user="62.65.192.84" anon="" timestamp="2008-07-20T14:30:46Z" size="61957" comment="/* Part VIII: Teach 2b Witch */"><tags /></rev><rev user="Aaronvangeffen" timestamp="2008-07-19T11:26:27Z" size="61957" comment="/* Part VIII: Teach 2b Witch */ grammar"><tags /></rev><rev minor="" user="Irmalover" timestamp="2008-07-19T10:57:44Z" size="61961" comment="missing information in the summary is added."><tags /></rev><rev user="Irmalover" timestamp="2008-07-19T10:44:32Z" size="61940" comment="Maqui is the original (Italian) spelling for the name of Ari&#039;s son."><tags /></rev><rev user="87.208.244.206" anon="" timestamp="2008-07-19T10:19:02Z" size="61937" comment="/* Part VIII: Teach To Be W.I.T.C.H. */  title changed according to a summary of sagas in the Italian Witch issue #87."><tags /></rev><rev user="87.208.244.206" anon="" timestamp="2008-07-19T10:16:56Z" size="61945" comment="From time to time We shows his love to Cornelia / Laura is a member of the Under-18, a group of youngsters hiding in an old subway station. Stephen is an old friend of Irma. (source: Witch issue #79)"><tags /></rev><rev user="87.208.244.206" anon="" timestamp="2008-07-19T10:04:48Z" size="61994" comment="/* Part VII: A New Power */     is changed according to a summary of saga titles in the Italian Witch issue #87"><tags /></rev><rev user="87.208.244.206" anon="" timestamp="2008-07-19T10:04:15Z" size="61996" comment="/* Part VI: The Ragorlang */     is changed according to a summary of saga titles in the Italian Witch issue #87"><tags /></rev><rev user="87.208.244.206" anon="" timestamp="2008-07-19T10:03:51Z" size="62000" comment="/* Part V: The Return of the Elements */     is changed according to a summary of saga titles in the Italian Witch issue #87"><tags /></rev><rev user="87.208.244.206" anon="" timestamp="2008-07-19T10:03:14Z" size="62006" comment="/* Part IV: Trial of the Oracle */    is changed according to a summary of saga titles in the Italian Witch issue #87"><tags /></rev><rev user="87.208.244.206" anon="" timestamp="2008-07-19T10:02:13Z" size="62018" comment="/* Part III: The Reign of Arkhanta */    is changed according a summary of saga titles in the Italian Witch issue #87"><tags /></rev><rev user="87.208.244.206" anon="" timestamp="2008-07-19T10:01:46Z" size="62024" comment="/* Part II: Nerissa&#039;s Revenge */  is changed according a summary of saga titles in the Italian Witch issue #87"><tags /></rev><rev user="87.208.244.206" anon="" timestamp="2008-07-19T09:59:55Z" size="62034" comment="/* Part I: The War in Meridian */  is changed according a summary of sagas in the Italian issue #87"><tags /></rev><rev user="87.208.244.206" anon="" timestamp="2008-07-19T09:55:25Z" size="62035" comment="update issues number"><tags /></rev><rev user="Irmalover" timestamp="2008-07-18T10:46:52Z" size="62035" comment="Emphasizing the fact that the Wall is original, not the Veil."><tags /></rev><rev user="Irmalover" timestamp="2008-07-18T10:18:45Z" size="62011" comment="/* Magical items */"><tags /></rev><rev user="Irmalover" timestamp="2008-07-18T10:05:33Z" size="61618" comment="/* Part VIII: Teach To Be W.I.T.C.H. */"><tags /></rev><rev user="87.208.244.206" anon="" timestamp="2008-07-18T09:39:52Z" size="61617" comment="/* Part VIII: Teach To Be W.I.T.C.H. */"><tags /></rev><rev user="87.208.244.206" anon="" timestamp="2008-07-18T08:47:43Z" size="61613" comment="/* Part VI: The Ragorlang */"><tags /></rev><rev user="86.128.77.196" anon="" timestamp="2008-07-16T15:11:54Z" size="61117" comment="/* Part VII: A New Power */"><tags /></rev><rev user="81.151.109.139" anon="" timestamp="2008-07-14T20:43:33Z" size="61032" comment="/* Guardians */"><tags /></rev><rev user="89.24.91.75" anon="" timestamp="2008-07-13T21:48:24Z" size="61032" comment="/* Notes */"><tags /></rev><rev user="87.208.244.206" anon="" timestamp="2008-07-11T19:21:43Z" size="61016" comment="/* Part VIII: Teach To Be W.I.T.C.H. */"><tags /></rev><rev minor="" user="Colonies Chris" timestamp="2008-07-11T08:28:36Z" size="61014" comment="sp, date &amp; link fixes, Replaced: completley → completely  using [[Project:AutoWikiBrowser|AWB]]"><tags /></rev><rev user="96.233.241.193" anon="" timestamp="2008-07-11T04:27:10Z" size="61042" comment="/* Part VIII: Teach To Be W.I.T.C.H. */"><tags /></rev><rev user="96.247.128.104" anon="" timestamp="2008-07-09T14:30:40Z" size="61025" comment="/* Part VIII: Teach To Be W.I.T.C.H. */"><tags /></rev><rev user="75.155.165.232" anon="" timestamp="2008-07-07T19:23:25Z" size="61020" comment="/* Former Guardians */"><tags /></rev><rev user="92.81.233.186" anon="" timestamp="2008-07-07T11:52:59Z" size="61022" comment="/* Part VII: A New Power */"><tags /></rev><rev user="92.81.233.186" anon="" timestamp="2008-07-07T11:47:16Z" size="60850" comment="/* Part VIII: Teach To Be W.I.T.C.H. */"><tags /></rev><rev user="92.81.233.186" anon="" timestamp="2008-07-07T11:46:43Z" size="60871" comment="/* Part VIII: Teach To Be W.I.T.C.H. */"><tags /></rev><rev user="75.15.28.247" anon="" timestamp="2008-07-06T22:45:41Z" size="60672" comment="/* Guardians */"><tags /></rev><rev user="121.96.189.131" anon="" timestamp="2008-07-05T04:57:07Z" size="60673" comment="/* Part VI: The Ragorlang */"><tags /></rev><rev user="96.237.116.224" anon="" timestamp="2008-07-04T20:01:20Z" size="60631" comment="/* Guardians */"><tags /></rev><rev user="189.60.6.168" anon="" timestamp="2008-07-04T00:42:57Z" size="60562" comment="/* Guardians */"><tags /></rev><rev user="Blunk" timestamp="2008-07-02T14:19:37Z" size="60529" comment="fix"><tags /></rev><rev user="24.168.197.140" anon="" timestamp="2008-07-02T05:29:01Z" size="60529" comment="/* Guardians */"><tags /></rev><rev user="24.168.197.140" anon="" timestamp="2008-07-02T05:23:16Z" size="60450" comment="/* Guardians */"><tags /></rev><rev user="71.162.87.37" anon="" timestamp="2008-07-01T21:29:23Z" size="60450" comment="/* Part V: The Return of the Elements */"><tags /></rev><rev user="71.162.87.37" anon="" timestamp="2008-07-01T21:28:24Z" size="60450" comment="/* Part IV: Trial of the Oracle */"><tags /></rev><rev user="71.162.87.37" anon="" timestamp="2008-07-01T20:13:36Z" size="60450" comment="/* Part II: Nerissa&#039;s Revenge */"><tags /></rev><rev user="71.162.87.37" anon="" timestamp="2008-07-01T20:12:03Z" size="60451" comment="/* Part I: The War in Meridian */"><tags /></rev><rev user="71.162.87.37" anon="" timestamp="2008-07-01T20:05:13Z" size="60451" comment="/* Part VI villains */"><tags /></rev><rev user="71.162.87.37" anon="" timestamp="2008-07-01T20:03:53Z" size="60455" comment="/* Part IV villains */"><tags /></rev><rev user="71.162.87.37" anon="" timestamp="2008-07-01T20:01:32Z" size="60447" comment="/* Part III villains */"><tags /></rev><rev user="71.162.87.37" anon="" timestamp="2008-07-01T19:56:27Z" size="60447" comment="/* Part II villains */"><tags /></rev><rev user="71.162.87.37" anon="" timestamp="2008-07-01T19:54:15Z" size="60533" comment="/* Part II villains */"><tags /></rev><rev user="71.162.87.37" anon="" timestamp="2008-07-01T19:46:10Z" size="60124" comment="/* Part I villains */"><tags /></rev><rev user="71.162.87.37" anon="" timestamp="2008-07-01T19:33:02Z" size="60048" comment="/* Guardians */"><tags /></rev><rev user="71.162.87.37" anon="" timestamp="2008-07-01T19:20:31Z" size="59802" comment="/* The Boys */"><tags /></rev><rev user="71.162.87.37" anon="" timestamp="2008-07-01T19:14:19Z" size="59797" comment="/* Council/Congregation of Kandrakar */"><tags /></rev><rev user="71.162.87.37" anon="" timestamp="2008-07-01T19:09:52Z" size="59797" comment="/* Former Guardians */"><tags /></rev><rev user="99.142.63.176" anon="" timestamp="2008-07-01T16:02:51Z" size="59783" comment="/* Guardians */"><tags /></rev><rev user="A Man In Black" timestamp="2008-06-29T02:22:39Z" size="59781" comment="fixed infobox"><tags /></rev><rev minor="" user="Gail" timestamp="2008-06-28T15:42:49Z" size="59791" comment="Reverted edits by [[Special:Contributions/72.89.147.118|72.89.147.118]] to last version by ClueBot (using [[WP:HG|Huggle]])"><tags /></rev><rev user="72.89.147.118" anon="" timestamp="2008-06-28T15:42:43Z" size="57786" comment="/* Former Guardians */"><tags /></rev><rev minor="" user="ClueBot" timestamp="2008-06-28T15:39:56Z" size="59791" comment="Reverting possible vandalism by [[Special:Contributions/72.89.147.118|72.89.147.118]] to version by 212.233.212.124. False positive? [[User:ClueBot/FalsePositives|Report it]]. Thanks, [[User:ClueBot]]. (427327) (Bot)"><tags /></rev><rev user="72.89.147.118" anon="" timestamp="2008-06-28T15:39:51Z" size="20101" comment="/* Characters */"><tags /></rev><rev user="212.233.212.124" anon="" timestamp="2008-06-26T17:28:09Z" size="59791" comment="/* Guardians */"><tags /></rev><rev user="TPIRFanSteve" timestamp="2008-06-25T01:07:33Z" size="59789" comment="/* Video Game */"><tags /></rev><rev user="TPIRFanSteve" timestamp="2008-06-25T01:07:08Z" size="59791" comment="/* Trivia */ Removed the section -- this isn&#039;t really important."><tags /></rev><rev minor="" user="TPIRFanSteve" timestamp="2008-06-25T01:06:34Z" size="60203" comment="/* Video Game */"><tags /></rev><rev user="TPIRFanSteve" timestamp="2008-06-25T01:05:59Z" size="60205" comment="/* New Power */ Gave the section a much-needed rewrite."><tags /></rev><rev user="203.84.180.62" anon="" timestamp="2008-06-23T10:14:01Z" size="60353" comment="/* Part VI: The Ragorlang */"><tags /></rev><rev user="69.137.35.193" anon="" timestamp="2008-06-22T22:12:17Z" size="60402" comment="/* Guardians */"><tags /></rev><rev minor="" user="Possum" timestamp="2008-06-21T17:42:18Z" size="60395" comment="Reverted 1 edit by [[Special:Contributions/Mustang p51|Mustang p51]]; Reverted unexplained removal of content."><tags /></rev><rev user="Mustang p51" timestamp="2008-06-21T17:41:36Z" size="44530" comment=""><tags /></rev><rev user="Bonadea" timestamp="2008-06-21T17:13:00Z" size="60395" comment="[[WP:UNDO|Undid]] revision 220779537 by [[Special:Contributions/Dragonguy93|Dragonguy93]] ([[User talk:Dragonguy93|talk]]) nn web content"><tags /></rev><rev minor="" user="Bonadea" timestamp="2008-06-21T17:12:03Z" size="60656" comment="Reverted edits by [[Special:Contributions/Mustang p51|Mustang p51]] ([[User talk:Mustang p51|talk]]) to last version by Dragonguy93"><tags /></rev><rev user="Mustang p51" timestamp="2008-06-21T17:06:15Z" size="0" comment="[[WP:AES|←]]​Blanked the page"><tags /></rev><rev user="Dragonguy93" timestamp="2008-06-21T15:18:01Z" size="60656" comment=""><tags /></rev><rev minor="" user="Metagraph" timestamp="2008-06-21T10:57:12Z" size="60395" comment="Reverted edits by [[Special:Contributions/213.219.80.185|213.219.80.185]] to last version by Blunk (using [[WP:HG|Huggle]])"><tags /></rev><rev user="213.219.80.185" anon="" timestamp="2008-06-21T10:57:03Z" size="60503" comment="/* External links */"><tags /></rev><rev user="Blunk" timestamp="2008-06-20T09:39:55Z" size="60395" comment="[[WP:UNDO|Undid]] revision 220339654 by [[Special:Contributions/80.235.64.74|80.235.64.74]] ([[User talk:80.235.64.74|talk]])"><tags /></rev><rev user="80.235.64.74" anon="" timestamp="2008-06-19T11:18:37Z" size="60583" comment=""><tags /></rev><rev user="79.17.190.160" anon="" timestamp="2008-06-18T06:29:19Z" size="60395" comment="Fan project"><tags /></rev><rev user="79.17.190.160" anon="" timestamp="2008-06-18T06:28:47Z" size="60696" comment="/* Influences */"><tags /></rev><rev minor="" user="Iridescent" timestamp="2008-06-13T15:25:52Z" size="60700" comment="Cleanup/[[WP:AWB/T|typo fixing]], typos fixed: sence → sense  using [[Project:AutoWikiBrowser|AWB]]"><tags /></rev><rev minor="" user="Nimbex" timestamp="2008-06-12T18:54:59Z" size="60702" comment="/* WITCHcast Podcast */  Correct spelling of &quot;Its&quot;."><tags /></rev><rev user="203.84.180.62" anon="" timestamp="2008-06-10T05:49:09Z" size="60703" comment="/* Issues, Titles and Storylines */"><tags /></rev><rev user="121.96.189.239" anon="" timestamp="2008-06-09T03:22:53Z" size="60547" comment="/* Part VI: The Ragorlang */"><tags /></rev><rev user="81.129.194.212" anon="" timestamp="2008-06-08T12:46:57Z" size="60550" comment="/* Part II villains */"><tags /></rev><rev user="58.69.89.164" anon="" timestamp="2008-06-08T03:59:24Z" size="60551" comment=""><tags /></rev><rev user="Chame45" timestamp="2008-06-08T01:19:37Z" size="60729" comment=""><tags /></rev><rev user="68.94.7.98" anon="" timestamp="2008-06-08T00:06:28Z" size="60821" comment="/* WITCHcast Podcast */"><tags /></rev></revisions></page></pages></query><limits revisions="500" /><query-continue><revisions rvstartid="217849736" /></query-continue></api>
